insitupy/__init__.py
insitupy/cli.py
insitupy/campaigns/__init__.py
insitupy/campaigns/campaign.py
insitupy/campaigns/snowex/__init__.py
insitupy/campaigns/snowex/snowex_campaign.py
insitupy/campaigns/snowex/snowex_metadata.py
insitupy/campaigns/snowex/snowex_profile_data_collection.py
insitupy/campaigns/snowex/snowexmetadatavariables.yaml
insitupy/campaigns/snowex/snowexprimaryvariables.yaml
insitupy/campaigns/snowex/sources.py
insitupy/campaigns/snowex/variables.py
insitupy/io/__init__.py
insitupy/io/dates.py
insitupy/io/locations.py
insitupy/io/metadata.py
insitupy/io/strings.py
insitupy/io/yaml_codes.py
insitupy/profiles/__init__.py
insitupy/profiles/base.py
insitupy/profiles/metadata.py
insitupy/variables/__init__.py
insitupy/variables/base_variables.py
insitupy/variables/basemetadatavariables.yaml
insitupy/variables/baseprimaryvariables.yaml
insitupy-0.4.5.dist-info/licenses/AUTHORS.rst
insitupy-0.4.5.dist-info/licenses/LICENSE
insitupy-0.4.5.dist-info/METADATA
insitupy-0.4.5.dist-info/WHEEL
insitupy-0.4.5.dist-info/entry_points.txt
insitupy-0.4.5.dist-info/top_level.txt
insitupy-0.4.5.dist-info/RECORD
