Metadata-Version: 2.4
Name: insitupy
Version: 0.4.5
Summary: Weave insitu data together
Home-page: https://github.com/m3works/insitupy
Author: M3 Works LLC
Author-email: info@m3works.io
License: MIT license
Keywords: insitupy
Classifier: Development Status :: 2 - Pre-Alpha
Classifier: Intended Audience :: Developers
Classifier: License :: OSI Approved :: MIT License
Classifier: Natural Language :: English
Classifier: Programming Language :: Python :: 3
Classifier: Programming Language :: Python :: 3.9
Classifier: Programming Language :: Python :: 3.10
Classifier: Programming Language :: Python :: 3.11
Classifier: Programming Language :: Python :: 3.12
Requires-Python: >=3.6
License-File: LICENSE
License-File: AUTHORS.rst
Requires-Dist: metloom<1.0,>=0.4.0
Requires-Dist: utm
Requires-Dist: numpy<2.0
Requires-Dist: attrs<25.0,>=24.2.0
Requires-Dist: PyYAML<7.0,>=6.0.2
Requires-Dist: pydash>=8.0.5
Dynamic: author
Dynamic: author-email
Dynamic: classifier
Dynamic: description
Dynamic: home-page
Dynamic: keywords
Dynamic: license
Dynamic: license-file
Dynamic: requires-dist
Dynamic: requires-python
Dynamic: summary
